cli_lite-0.11.3.dist-info/METADATA
cli_lite-0.11.3.dist-info/WHEEL
cli_lite-0.11.3.dist-info/entry_points.txt
cli_lite-0.11.3.dist-info/licenses/LICENSE
clilte/__init__.py
clilte/builtin.py
clilte/core.py
clilte/formatter.py
cli_lite-0.11.3.dist-info/RECORD
