Metadata-Version: 2.1
Name: cli-lite
Version: 0.11.3
Summary: A simple framework to build a cli tool, base on Alconna
Keywords: commandline,cli-tool,plugin,cli,litecli
Author-Email: RF-Tar-Railt <rf_tar_railt@qq.com>
License: MIT
Classifier: Development Status :: 4 - Beta
Classifier: License :: OSI Approved :: MIT License
Classifier: Operating System :: OS Independent
Classifier: Programming Language :: Python :: 3.10
Classifier: Programming Language :: Python :: 3.11
Classifier: Programming Language :: Python :: 3.8
Classifier: Programming Language :: Python :: 3.9
Project-URL: Homepage, https://github.com/RF-Tar-Railt/cli-lite
Project-URL: Bug Reports, https://github.com/RF-Tar-Railt/cli-lite/issues
Project-URL: Source, https://github.com/RF-Tar-Railt/cli-lite
Requires-Python: >=3.9
Requires-Dist: arclet-alconna>=1.8.43
Requires-Dist: arclet-alconna-tools>=0.7.11
Requires-Dist: importlib-metadata>=3.6.0
